{
  "cookies": [
    {
      "name": "rur",
      "value": "\"NCG\\05445767428267\\0541786678290:01fe7056395b8f5b53c9ad41247241f5f3f14d8215dcf3bf5d915e7b02adcb8ba5312e6f\"",
      "domain": ".instagram.com",
      "path": "/",
      "expires": -1,
      "size": 110,
      "httpOnly": true,
      "secure": true,
      "session": true,
      "sameSite": "Lax",
      "priority": "Medium",
      "sameParty": false,
      "sourceScheme": "Secure"
    },
    {
      "name": "mid",
      "value": "aJvVtgAEAAFWJbNzaphpYeGS7raI",
      "domain": ".instagram.com",
      "path": "/",
      "expires": 1789603254,
      "size": 31,
      "httpOnly": false,
      "secure": true,
      "session": false,
      "priority": "Medium",
      "sameParty": false,
      "sourceScheme": "Secure"
    },
    {
      "name": "sessionid",
      "value": "45767428267%3AIPQzSJmiqF4XJ0%3A28%3AAYeHkYv7NLR_wiYvcPBZ10lDMOz99XOiPK1oS8Snfg",
      "domain": ".instagram.com",
      "path": "/",
      "expires": 1786663256.918911,
      "size": 87,
      "httpOnly": true,
      "secure": true,
      "session": false,
      "priority": "Medium",
      "sameParty": false,
      "sourceScheme": "Secure"
    },
    {
      "name": "ps_n",
      "value": "1",
      "domain": ".instagram.com",
      "path": "/",
      "expires": 1789688392.56532,
      "size": 5,
      "httpOnly": true,
      "secure": true,
      "session": false,
      "sameSite": "None",
      "priority": "Medium",
      "sameParty": false,
      "sourceScheme": "Secure"
    },
    {
      "name": "dpr",
      "value": "1",
      "domain": ".instagram.com",
      "path": "/",
      "expires": 1755747085,
      "size": 4,
      "httpOnly": false,
      "secure": true,
      "session": false,
      "sameSite": "None",
      "priority": "Medium",
      "sameParty": false,
      "sourceScheme": "Secure"
    },
    {
      "name": "ps_l",
      "value": "1",
      "domain": ".instagram.com",
      "path": "/",
      "expires": 1789688392.565284,
      "size": 5,
      "httpOnly": true,
      "secure": true,
      "session": false,
      "sameSite": "Lax",
      "priority": "Medium",
      "sameParty": false,
      "sourceScheme": "Secure"
    },
    {
      "name": "ig_nrcb",
      "value": "1",
      "domain": ".instagram.com",
      "path": "/",
      "expires": 1786579256.565563,
      "size": 8,
      "httpOnly": false,
      "secure": true,
      "session": false,
      "priority": "Medium",
      "sameParty": false,
      "sourceScheme": "Secure"
    },
    {
      "name": "wd",
      "value": "1280x800",
      "domain": ".instagram.com",
      "path": "/",
      "expires": 1755747085,
      "size": 10,
      "httpOnly": false,
      "secure": true,
      "session": false,
      "sameSite": "Lax",
      "priority": "Medium",
      "sameParty": false,
      "sourceScheme": "Secure"
    },
    {
      "name": "datr",
      "value": "ttWbaDCeNZAOi6KWmSLSoGLH",
      "domain": ".instagram.com",
      "path": "/",
      "expires": 1789603254.081049,
      "size": 28,
      "httpOnly": true,
      "secure": true,
      "session": false,
      "sameSite": "None",
      "priority": "Medium",
      "sameParty": false,
      "sourceScheme": "Secure"
    },
    {
      "name": "ig_did",
      "value": "52C76DCB-2953-42BD-B84B-FBCBC3B1EAFD",
      "domain": ".instagram.com",
      "path": "/",
      "expires": 1786579254.081071,
      "size": 42,
      "httpOnly": true,
      "secure": true,
      "session": false,
      "sameSite": "None",
      "priority": "Medium",
      "sameParty": false,
      "sourceScheme": "Secure"
    },
    {
      "name": "ds_user_id",
      "value": "45767428267",
      "domain": ".instagram.com",
      "path": "/",
      "expires": 1762918290.615548,
      "size": 21,
      "httpOnly": false,
      "secure": true,
      "session": false,
      "sameSite": "None",
      "priority": "Medium",
      "sameParty": false,
      "sourceScheme": "Secure"
    },
    {
      "name": "csrftoken",
      "value": "iORAXmi9HJbpTy69BO6wpD",
      "domain": ".instagram.com",
      "path": "/",
      "expires": 1789702290.615267,
      "size": 31,
      "httpOnly": false,
      "secure": true,
      "session": false,
      "priority": "Medium",
      "sameParty": false,
      "sourceScheme": "Secure"
    }
  ],
  "storage": {
    "localStorage": {
      "chatd-deviceid": "e1053ca7-ef00-4cef-ae34-9ba04eaa09f6",
      "hb_timestamp": "1755142285821",
      "IGSession": "jtdb89:1755144085746",
      "fr": "ASCXMPsyGVK2HiKJfNVWvnphUHMRgAXI4poJpapS1qaJyBbQeTgJA_QHHhcC-i4AMxTtQCoWOWCbR1UjO9SXV6ricwDxeOrn5Lal9slJ_mxor_uH8QlTxoKftiqMP9qqSqJL3mU",
      "pixel_fire_ts": "1755142286079",
      "signal_flush_timestamp": "1755142285826",
      "Session": "1c785q:1755142320746",
      "has_interop_upgraded": "{\"lastCheckedAt\":1755142284328,\"status\":true}",
      "banzai:last_storage_flush": "1755142284509.7"
    },
    "sessionStorage": {
      "original_referrer": "",
      "IGTabId": "klqydc",
      "TabId": "n4on8b",
      "www-claim-v2": "hmac.AR0VvhO7K7gewx9a0qsoBNHy2YrA6GRd5Ft5q0YadPV00_qk"
    }
  }
}